AUTHORS
CHANGELOG.txt
DESCRIPTION
LICENSE
MANIFEST.in
setup.py
django_pypi.egg-info/PKG-INFO
django_pypi.egg-info/SOURCES.txt
django_pypi.egg-info/dependency_links.txt
django_pypi.egg-info/requires.txt
django_pypi.egg-info/top_level.txt
pypi/.DS_Store
pypi/__init__.py
pypi/admin.py
pypi/models.py
pypi/tasks.py
pypi/management/__init__.py
pypi/management/commands/__init__.py
pypi/management/commands/pypi_refresh.py
pypi/migrations/0001_initial.py
pypi/migrations/0002_auto__chg_field_release_packagetype.py
pypi/migrations/0003_auto__chg_field_version_version.py
pypi/migrations/0004_auto__chg_field_version_version.py
pypi/migrations/0005_auto__chg_field_release_comment_text.py
pypi/migrations/__init__.py