Metadata-Version: 1.0
Name: django-pypi
Version: 0.1
Summary: VAR_DESCRIPTION
